paginated_modelformset
