Metadata-Version: 1.1
Name: django-paginated-modelformset
Version: 0.0.2
Summary: An attempt to add pagination to Django Model Formsets.
Home-page: https://github.com/creafz/django-paginated-modelformset
Author: Alex Parinov
Author-email: creafz@gmail.com
License: MIT License
Download-URL: https://github.com/creafz/django-paginated-modelformset/tarball/0.0.2
Keywords: django,form,formset,modelformset,pagination
Platform: UNKNOWN
Classifier: Development Status :: 3 - Alpha
Classifier: Environment :: Web Environment
Classifier: Framework :: Django
Classifier: Intended Audience :: Developers
Classifier: License :: OSI Approved :: MIT License
Classifier: Operating System :: OS Independent
Classifier: Programming Language :: Python
Classifier: Programming Language :: Python :: 2
Classifier: Programming Language :: Python :: 2.6
Classifier: Programming Language :: Python :: 2.7
Classifier: Programming Language :: Python :: 3
Classifier: Programming Language :: Python :: 3.0
Classifier: Programming Language :: Python :: 3.1
Classifier: Programming Language :: Python :: 3.2
Classifier: Programming Language :: Python :: 3.3
Classifier: Programming Language :: Python :: 3.4
Classifier: Topic :: Internet :: WWW/HTTP
Classifier: Topic :: Internet :: WWW/HTTP :: Dynamic Content
